Metadata-Version: 1.0
Name: canonicalwebteam.snapstoreapi
Version: 0.4.4
Summary: Snapstore API
Home-page: https://github.com/canonical-webteam/snapstore-api
Author: Canonical Webteam
Author-email: thomas.bille@canonical.com
License: AGPLv3
Platform: UNKNOWN
